kissmanga/__init__.py
kissmanga-1.0.9.dist-info/LICENSE
kissmanga-1.0.9.dist-info/METADATA
kissmanga-1.0.9.dist-info/WHEEL
kissmanga-1.0.9.dist-info/top_level.txt
kissmanga-1.0.9.dist-info/RECORD
