Metadata-Version: 2.1
Name: kissmanga
Version: 1.0.9
Summary: An Unofficial Python API Library to Download Manga  for FREE...
Home-page: https://github.com/otakatsu/kissmangaapi.git
Author: otakatsu
Author-email: moezilla@otakatsu.studio
License: License :: OSI Approved :: GNU Lesser General Public License v3 (LGPLv3)
Classifier: Programming Language :: Python :: 3
Classifier: Programming Language :: Python :: 3.6
Classifier: Programming Language :: Python :: 3.7
Classifier: Programming Language :: Python :: 3.8
Classifier: Programming Language :: Python :: 3.9
Classifier: Operating System :: OS Independent
Requires-Python: >=3.6
License-File: LICENSE
Requires-Dist: bs4
Requires-Dist: requests
Requires-Dist: requests-html
